heyoo/__init__.py
heyoo-0.1.1.dist-info/LICENSE
heyoo-0.1.1.dist-info/METADATA
heyoo-0.1.1.dist-info/WHEEL
heyoo-0.1.1.dist-info/top_level.txt
heyoo-0.1.1.dist-info/RECORD
