Metadata-Version: 2.1
Name: heyoo
Version: 0.1.1
Summary: Opensource Python wrapper to WhatsApp Cloud API
Home-page: https://github.com/Neurotech-HQ/heyoo
Download-URL: https://github.com/Neurotech-HQ/heyoo/archive/refs/tags/v0.4.tar.gz
Author: Jordan Kalebu
Author-email: isaackeinstein@gmail.com
License: MIT
Keywords: heyoo,heyoo-libary,WhatsApp Cloud API Wrapper,PyWhatsApp,WhatsApp API in Python
Classifier: Development Status :: 3 - Alpha
Classifier: Intended Audience :: Developers
Classifier: Topic :: Software Development :: Build Tools
Classifier: License :: OSI Approved :: MIT License
Classifier: Programming Language :: Python :: 3.6
Classifier: Programming Language :: Python :: 3.7
Classifier: Programming Language :: Python :: 3.8
Classifier: Programming Language :: Python :: 3.9
Classifier: Programming Language :: Python :: 3.10
Requires-Python: >=3.6
License-File: LICENSE
Requires-Dist: requests >=2.28.1
Requires-Dist: requests-toolbelt >=0.9.1
Requires-Dist: colorama
Requires-Dist: typing ; python_version < "3.5"
Provides-Extra: test
Requires-Dist: python-dotenv ==0.20.0 ; extra == 'test'
Requires-Dist: pytest ==7.1.3 ; extra == 'test'
